camper_dramkit/__init__.py
camper_dramkit/camper_annotate.py
camper_dramkit/camper_distill.py
camper_dramkit/combine_annotations_lowmem.py
camper_dramkit/data/CAMPER.hmm
camper_dramkit/data/CAMPER_blast.faa
camper_dramkit/data/CAMPER_blast_scores.tsv
camper_dramkit/data/CAMPER_distillate.tsv
camper_dramkit/data/CAMPER_hmm_scores.tsv
camper_dramkit-1.0.0.dist-info/METADATA
camper_dramkit-1.0.0.dist-info/WHEEL
camper_dramkit-1.0.0.dist-info/entry_points.txt
camper_dramkit-1.0.0.dist-info/top_level.txt
camper_dramkit-1.0.0.dist-info/RECORD
