Metadata-Version: 2.1
Name: camper-dramkit
Version: 1.0.0
Summary: A tool to use the CAMPER dataset
Home-page: https://github.com/WrightonLabCSU/CAMPER
Download-URL: https://github.com/WrightonLabCSU/CAMPER/tarball/1.0.0
Author: Rory Flynn
Author-email: rory.flynn@colostate.edu
Requires-Python: >=3.8
Requires-Dist: pandas
Requires-Dist: altair
Requires-Dist: sqlalchemy
Requires-Dist: networkx
Requires-Dist: openpyxl
Requires-Dist: numpy
Requires-Dist: click
